build_.py
evaluate.py
measure.py
sample.py
train.py
utils.py
data/af2fs.py
data/atlas.py
data/fast_folding.py
data/hybrid.py
data/md_cath.py
fast_folders/evaluate_free_energy.py
nn/deepjump.py
nn/interpolant.py
deepjump-0.1.0.dist-info/METADATA
deepjump-0.1.0.dist-info/WHEEL
deepjump-0.1.0.dist-info/top_level.txt
deepjump-0.1.0.dist-info/RECORD
