Metadata-Version: 2.1
Name: deepjump
Version: 0.1.0
Summary: Accelerated Protein Dynamics Simulation
Author: 
Classifier: Intended Audience :: Developers
Classifier: Programming Language :: Python
Classifier: Programming Language :: Python :: 3.9
Classifier: Programming Language :: Python :: 3.10
Classifier: Programming Language :: Python :: 3.11
Classifier: Programming Language :: Python :: 3.12
Requires-Python: >=3.9
Requires-Dist: numpy
Requires-Dist: e3nn-jax
Requires-Dist: ordered-set
Requires-Dist: flax
Requires-Dist: einops
Requires-Dist: wandb
Provides-Extra: dev
Provides-Extra: test
Requires-Dist: pytest ; extra == 'test'
